{
  "tasks": [
    {
      "id": "1",
      "text": "AI Conference",
      "day": "March 18th at 10:00am",
      "reminder": false
    },
    {
      "id": "5",
      "text": "Car Wash",
      "day": "April 1st at 3:00pm",
      "reminder": false
    },
    {
      "id": "38b1",
      "text": "Earnings Report",
      "day": "March 25th at 4:00pm",
      "reminder": true
    },
    {
      "id": "0d00",
      "text": "Mar 28th Expiry, 30 Call",
      "day": "March 25th at 3:50pm",
      "reminder": true
    },
    {
      "id": "1e53",
      "text": "Apr 4th Expiry, 24 Put",
      "day": "March 26th at 3:00pm",
      "reminder": true
    }
  ]
}